Metadata-Version: 2.4
Name: mattermost
Version: 10.11.0
Summary: Mattermost API bindings
Home-page: https://git.somenet.org/pub/jan/mattermost-api-python.git
Author: someone
Author-email: someone@somenet.org
Classifier: Programming Language :: Python :: 3
Classifier: License :: OSI Approved :: MIT License
Classifier: Operating System :: OS Independent
Requires-Python: >=3.7
License-File: LICENSE.txt
Requires-Dist: requests
Requires-Dist: websockets
Dynamic: author
Dynamic: author-email
Dynamic: classifier
Dynamic: description
Dynamic: description-content-type
Dynamic: home-page
Dynamic: license-file
Dynamic: requires-dist
Dynamic: requires-python
Dynamic: summary
